{"cameraMode":{"drawMode":0,"name":"Shaded","section":"Shading Mode"},"sceneLighting":false,"audioPlay":false,"sceneViewState":{"showFog":true,"showMaterialUpdate":false,"showSkybox":false,"showFlares":true,"showImageEffects":true,"showParticleSystems":true},"in2DMode":false,"pivot":{"x":34.03956604003906,"y":-24.38626480102539,"z":1.8717122077941895},"rotation":{"x":0.2548263370990753,"y":0.6944133043289185,"z":-0.29180073738098147,"w":0.6064180135726929},"size":62.26297378540039,"orthographic":false}